ascript/__init__.py
ascript/ios/__init__.py
ascript/ios/action.py
ascript/ios/node.py
ascript/ios/system.py
ascript/ios/developer/.DS_Store
ascript/ios/developer/__init__.py
ascript/ios/developer/main.py
ascript/ios/developer/server.py
ascript/ios/developer/ws.py
ascript/ios/developer/__pycache__/__init__.cpython-311.pyc
ascript/ios/developer/__pycache__/__init__.cpython-312.pyc
ascript/ios/developer/__pycache__/__init__.cpython-38.pyc
ascript/ios/developer/__pycache__/server.cpython-311.pyc
ascript/ios/developer/__pycache__/server.cpython-312.pyc
ascript/ios/developer/__pycache__/server.cpython-38.pyc
ascript/ios/developer/__pycache__/ws.cpython-311.pyc
ascript/ios/developer/__pycache__/ws.cpython-312.pyc
ascript/ios/developer/__pycache__/ws.cpython-38.pyc
ascript/ios/developer/api/__init__.py
ascript/ios/developer/api/api_file.py
ascript/ios/developer/api/api_module.py
ascript/ios/developer/api/api_node.py
ascript/ios/developer/api/api_screen.py
ascript/ios/developer/api/dao.py
ascript/ios/developer/api/utils.py
ascript/ios/developer/api/__pycache__/__init__.cpython-311.pyc
ascript/ios/developer/api/__pycache__/__init__.cpython-312.pyc
ascript/ios/developer/api/__pycache__/__init__.cpython-38.pyc
ascript/ios/developer/api/__pycache__/api_file.cpython-311.pyc
ascript/ios/developer/api/__pycache__/api_file.cpython-312.pyc
ascript/ios/developer/api/__pycache__/api_file.cpython-38.pyc
ascript/ios/developer/api/__pycache__/api_module.cpython-311.pyc
ascript/ios/developer/api/__pycache__/api_module.cpython-312.pyc
ascript/ios/developer/api/__pycache__/api_module.cpython-38.pyc
ascript/ios/developer/api/__pycache__/api_node.cpython-311.pyc
ascript/ios/developer/api/__pycache__/api_node.cpython-312.pyc
ascript/ios/developer/api/__pycache__/api_node.cpython-38.pyc
ascript/ios/developer/api/__pycache__/api_screen.cpython-311.pyc
ascript/ios/developer/api/__pycache__/api_screen.cpython-312.pyc
ascript/ios/developer/api/__pycache__/api_screen.cpython-38.pyc
ascript_ios-1.2.2.dist-info/METADATA
ascript_ios-1.2.2.dist-info/WHEEL
ascript_ios-1.2.2.dist-info/top_level.txt
ascript_ios-1.2.2.dist-info/RECORD
