Metadata-Version: 2.1
Name: ascript-ios
Version: 1.2.2
Summary: ascript IOS python库
Home-page: https://airscript.cn/
Author: aojoy
Author-email: aojoytec@163.com
License: MIT
Keywords: python,ascript
Classifier: Programming Language :: Python :: 3
Classifier: License :: OSI Approved :: MIT License
Classifier: Operating System :: OS Independent
Requires-Dist: blinker ==1.8.2
Requires-Dist: certifi ==2024.7.4
Requires-Dist: charset-normalizer ==3.3.2
Requires-Dist: click ==8.1.7
Requires-Dist: decorator ==5.1.1
Requires-Dist: Flask ==3.0.3
Requires-Dist: gevent ==24.2.1
Requires-Dist: greenlet ==3.0.3
Requires-Dist: idna ==3.7
Requires-Dist: itsdangerous ==2.2.0
Requires-Dist: Jinja2 ==3.1.4
Requires-Dist: MarkupSafe ==2.1.5
Requires-Dist: numpy ==1.24.0
Requires-Dist: opencv-python ==4.10.0.84
Requires-Dist: pillow ==10.4.0
Requires-Dist: py ==1.11.0
Requires-Dist: requests ==2.32.3
Requires-Dist: retry ==0.9.2
Requires-Dist: urllib3 ==2.2.2
Requires-Dist: websockets ==12.0
Requires-Dist: Werkzeug ==3.0.3
Requires-Dist: zope.event ==5.0
Requires-Dist: zope.interface ==6.4.post2
Requires-Dist: Deprecated >=1.2.6
Requires-Dist: retry
Requires-Dist: construct >=2
Requires-Dist: six
